phone_a_friend_mcp_server/__init__.py
phone_a_friend_mcp_server/__main__.py
phone_a_friend_mcp_server/config.py
phone_a_friend_mcp_server/server.py
phone_a_friend_mcp_server/client/__init__.py
phone_a_friend_mcp_server/tools/__init__.py
phone_a_friend_mcp_server/tools/base_tools.py
phone_a_friend_mcp_server/tools/fax_tool.py
phone_a_friend_mcp_server/tools/phone_tool.py
phone_a_friend_mcp_server/tools/tool_manager.py
phone_a_friend_mcp_server/utils/__init__.py
phone_a_friend_mcp_server/utils/context_builder.py
phone_a_friend_mcp_server-0.2.0.dist-info/METADATA
phone_a_friend_mcp_server-0.2.0.dist-info/WHEEL
phone_a_friend_mcp_server-0.2.0.dist-info/entry_points.txt
phone_a_friend_mcp_server-0.2.0.dist-info/licenses/LICENSE
phone_a_friend_mcp_server-0.2.0.dist-info/RECORD
