Metadata-Version: 2.4
Name: phone-a-friend-mcp-server
Version: 0.2.0
Summary: MCP Server for Phone-a-Friend assistance
Project-URL: GitHub, https://github.com/abhishekbhakat/phone-a-friend-mcp-server
Project-URL: Issues, https://github.com/abhishekbhakat/phone-a-friend-mcp-server/issues
Author-email: Abhishek Bhakat <abhishek.bhakat@hotmail.com>
License-Expression: MIT
License-File: LICENSE
Classifier: Development Status :: 3 - Alpha
Classifier: Operating System :: OS Independent
Classifier: Programming Language :: Python :: 3.10
Classifier: Programming Language :: Python :: 3.11
Classifier: Programming Language :: Python :: 3.12
Requires-Python: >=3.11
Requires-Dist: aiofiles>=24.1.0
Requires-Dist: aiohttp>=3.12.7
Requires-Dist: click>=8.2.1
Requires-Dist: mcp>=1.9.2
Requires-Dist: pathspec>=0.12.1
Requires-Dist: pydantic-ai-slim[anthropic,google,openai]>=0.2.14
Requires-Dist: pydantic>=2.11.5
Requires-Dist: pyyaml>=6.0.0
